omnitagger/__init__.py
omnitagger/metatagger.py
omnitagger/omnitagger.py
omnitagger-2.1.5.data/scripts/omnitagger
omnitagger-2.1.5.dist-info/METADATA
omnitagger-2.1.5.dist-info/RECORD
omnitagger-2.1.5.dist-info/WHEEL
omnitagger-2.1.5.dist-info/top_level.txt
