Metadata-Version: 2.1
Name: omnitagger
Version: 2.1.5
Summary: 
Requires-Dist: prettytable (>=0.7.2)
Requires-Dist: mutagen (>=1.36)
Requires-Dist: logger (>=1.4)
Requires-Dist: titlecase (>=0.8.1)
Requires-Dist: argparse (>=1.4.0)
Requires-Dist: pyacoustid (>=1.1.4)
